gputils.py
gputils-1.0.6.dist-info/DESCRIPTION.rst
gputils-1.0.6.dist-info/METADATA
gputils-1.0.6.dist-info/RECORD
gputils-1.0.6.dist-info/WHEEL
gputils-1.0.6.dist-info/metadata.json
gputils-1.0.6.dist-info/top_level.txt
