Metadata-Version: 2.0
Name: gputils
Version: 1.0.6
Summary: Variety of utilities that may come handy in diverse projects. 
Home-page: https://github.com/guiem/gputils
Author: Guiem Bosch
Author-email: g@guiem.info
License: UNKNOWN
Platform: UNKNOWN
Classifier: Development Status :: 5 - Production/Stable
Classifier: Intended Audience :: Developers
Classifier: Topic :: Software Development :: Build Tools
Classifier: License :: OSI Approved :: MIT License
Classifier: Programming Language :: Python :: 3
Requires-Dist: numpy
Requires-Dist: pandas
Provides-Extra: test
Requires-Dist: coverage; extra == 'test'
